gitpod/__init__.py
gitpod/_base_client.py
gitpod/_client.py
gitpod/_compat.py
gitpod/_constants.py
gitpod/_exceptions.py
gitpod/_files.py
gitpod/_models.py
gitpod/_qs.py
gitpod/_resource.py
gitpod/_response.py
gitpod/_streaming.py
gitpod/_types.py
gitpod/_version.py
gitpod/pagination.py
gitpod/py.typed
gitpod/_decoders/jsonl.py
gitpod/_utils/__init__.py
gitpod/_utils/_compat.py
gitpod/_utils/_datetime_parse.py
gitpod/_utils/_logs.py
gitpod/_utils/_proxy.py
gitpod/_utils/_reflection.py
gitpod/_utils/_resources_proxy.py
gitpod/_utils/_streams.py
gitpod/_utils/_sync.py
gitpod/_utils/_transform.py
gitpod/_utils/_typing.py
gitpod/_utils/_utils.py
gitpod/lib/.keep
gitpod/lib/__init__.py
gitpod/lib/automation.py
gitpod/lib/disposables.py
gitpod/lib/environment.py
gitpod/lib/runner.py
gitpod/resources/__init__.py
gitpod/resources/accounts.py
gitpod/resources/agents.py
gitpod/resources/editors.py
gitpod/resources/errors.py
gitpod/resources/events.py
gitpod/resources/gateways.py
gitpod/resources/identity.py
gitpod/resources/prebuilds.py
gitpod/resources/secrets.py
gitpod/resources/usage.py
gitpod/resources/environments/__init__.py
gitpod/resources/environments/classes.py
gitpod/resources/environments/environments.py
gitpod/resources/environments/automations/__init__.py
gitpod/resources/environments/automations/automations.py
gitpod/resources/environments/automations/services.py
gitpod/resources/environments/automations/tasks/__init__.py
gitpod/resources/environments/automations/tasks/executions.py
gitpod/resources/environments/automations/tasks/tasks.py
gitpod/resources/groups/__init__.py
gitpod/resources/groups/groups.py
gitpod/resources/groups/memberships.py
gitpod/resources/groups/role_assignments.py
gitpod/resources/groups/shares.py
gitpod/resources/organizations/__init__.py
gitpod/resources/organizations/custom_domains.py
gitpod/resources/organizations/domain_verifications.py
gitpod/resources/organizations/invites.py
gitpod/resources/organizations/organizations.py
gitpod_sdk-0.7.0.dist-info/METADATA
gitpod_sdk-0.7.0.dist-info/WHEEL
gitpod_sdk-0.7.0.dist-info/licenses/LICENSE
gitpod_sdk-0.7.0.dist-info/RECORD
